briann/__init__.py
briann/GUI/__init__.py
briann/GUI/model_explorer.py
briann/network/__init__.py
briann/network/area_transformations.py
briann/network/connection_transformations.py
briann/network/core.py
briann/training/__init__.py
briann/utilities/__init__.py
briann/utilities/callbacks.py
briann/utilities/core.py
briann/utilities/file_management.py
briann/utilities/playground.py
briann/utilities/random.py
briann-0.0.8.dist-info/licenses/LICENSE
briann-0.0.8.dist-info/METADATA
briann-0.0.8.dist-info/WHEEL
briann-0.0.8.dist-info/top_level.txt
briann-0.0.8.dist-info/RECORD
